README.md
setup.py
uyghur_language_tools/UyghurLanguageTools.py
uyghur_language_tools/__init__.py
uyghur_tili_quralliri.egg-info/PKG-INFO
uyghur_tili_quralliri.egg-info/SOURCES.txt
uyghur_tili_quralliri.egg-info/dependency_links.txt
uyghur_tili_quralliri.egg-info/top_level.txt