Metadata-Version: 2.1
Name: uyghur-tili-quralliri
Version: 0.1.4
Summary: uyghur language writing and processing tool box ...
Home-page: https://github.com/kompasim/uyghur-tili-quralliri
Author: kompasim
Author-email: kompasim@163.com
License: MIT Licence
Keywords: uyghur,uighur,til,yeziq,qural,language,tools
Platform: any
Classifier: Programming Language :: Python :: 3
Classifier: License :: OSI Approved :: MIT License
Classifier: Operating System :: OS Independent
